plone.app.locales-6.1.1-py3.11-nspkg.pth
plone/app/locales/__init__.py
plone/app/locales/configure.zcml
plone/app/locales/locales/cmfeditions-manual.pot
plone/app/locales/locales/cmfeditions.pot
plone/app/locales/locales/cmfplacefulworkflow-manual.pot
plone/app/locales/locales/cmfplacefulworkflow.pot
plone/app/locales/locales/plone-generated.pot
plone/app/locales/locales/plone-manual.pot
plone/app/locales/locales/plone.pot
plone/app/locales/locales/plonefrontpage.pot
plone/app/locales/locales/plonelocales.pot
plone/app/locales/locales/widgets.pot
plone/app/locales/locales/af/LC_MESSAGES/cmfeditions.mo
plone/app/locales/locales/af/LC_MESSAGES/cmfeditions.po
plone/app/locales/locales/af/LC_MESSAGES/cmfplacefulworkflow.mo
plone/app/locales/locales/af/LC_MESSAGES/cmfplacefulworkflow.po
plone/app/locales/locales/af/LC_MESSAGES/plone.mo
plone/app/locales/locales/af/LC_MESSAGES/plone.po
plone/app/locales/locales/af/LC_MESSAGES/plonefrontpage.mo
plone/app/locales/locales/af/LC_MESSAGES/plonefrontpage.po
plone/app/locales/locales/af/LC_MESSAGES/plonelocales.mo
plone/app/locales/locales/af/LC_MESSAGES/plonelocales.po
plone/app/locales/locales/af/LC_MESSAGES/widgets.mo
plone/app/locales/locales/af/LC_MESSAGES/widgets.po
plone/app/locales/locales/ar/LC_MESSAGES/cmfeditions.mo
plone/app/locales/locales/ar/LC_MESSAGES/cmfeditions.po
plone/app/locales/locales/ar/LC_MESSAGES/cmfplacefulworkflow.mo
plone/app/locales/locales/ar/LC_MESSAGES/cmfplacefulworkflow.po
plone/app/locales/locales/ar/LC_MESSAGES/plone.mo
plone/app/locales/locales/ar/LC_MESSAGES/plone.po
plone/app/locales/locales/ar/LC_MESSAGES/plonefrontpage.mo
plone/app/locales/locales/ar/LC_MESSAGES/plonefrontpage.po
plone/app/locales/locales/ar/LC_MESSAGES/plonelocales.mo
plone/app/locales/locales/ar/LC_MESSAGES/plonelocales.po
plone/app/locales/locales/ar/LC_MESSAGES/widgets.mo
plone/app/locales/locales/ar/LC_MESSAGES/widgets.po
plone/app/locales/locales/bg/LC_MESSAGES/cmfeditions.mo
plone_app_locales-6.1.1.dist-info/METADATA
plone_app_locales-6.1.1.dist-info/WHEEL
plone_app_locales-6.1.1.dist-info/namespace_packages.txt
plone_app_locales-6.1.1.dist-info/top_level.txt
plone_app_locales-6.1.1.dist-info/RECORD
